function_stream/__init__.py
function_stream/config.py
function_stream/context.py
function_stream/function.py
function_stream/metrics.py
function_stream/module.py
function_stream-0.6.0rc2.dist-info/METADATA
function_stream-0.6.0rc2.dist-info/WHEEL
function_stream-0.6.0rc2.dist-info/top_level.txt
function_stream-0.6.0rc2.dist-info/RECORD
