Metadata-Version: 2.4
Name: function-stream
Version: 0.6.0rc2
Summary: FunctionStream SDK is a powerful Python library for building and deploying serverless streaming functions that runs on Function Stream platform.
Author: FunctionStream Org
Maintainer: FunctionStream Org
License: Apache-2.0
Project-URL: Homepage, https://github.com/functionstream/function-stream
Project-URL: Documentation, https://github.com/functionstream/function-stream/tree/main/sdks/fs-python
Project-URL: Repository, https://github.com/functionstream/function-stream
Project-URL: Bug Tracker, https://github.com/functionstream/function-stream/issues
Project-URL: Source Code, https://github.com/functionstream/function-stream
Keywords: serverless,functions,pulsar,event-driven,streaming
Classifier: Development Status :: 4 - Beta
Classifier: Intended Audience :: Developers
Classifier: License :: OSI Approved :: Apache Software License
Classifier: Operating System :: OS Independent
Classifier: Programming Language :: Python :: 3
Classifier: Programming Language :: Python :: 3.9
Classifier: Programming Language :: Python :: 3.10
Classifier: Programming Language :: Python :: 3.11
Classifier: Programming Language :: Python :: 3.12
Classifier: Topic :: Software Development :: Libraries :: Python Modules
Classifier: Topic :: System :: Distributed Computing
Classifier: Topic :: Internet :: WWW/HTTP :: HTTP Servers
Classifier: Topic :: System :: Networking
Requires-Python: >=3.9
Requires-Dist: pulsar-client>=3.0.0
Requires-Dist: pyyaml>=6.0
Requires-Dist: aiohttp>=3.8.0
Requires-Dist: pydantic>=2.0.0
Provides-Extra: dev
Requires-Dist: pytest>=7.0.0; extra == "dev"
Requires-Dist: pytest-asyncio>=0.21.0; extra == "dev"
Requires-Dist: black>=22.0.0; extra == "dev"
Requires-Dist: flake8>=5.0.0; extra == "dev"
Requires-Dist: mypy>=1.0.0; extra == "dev"
Requires-Dist: pre-commit>=3.0.0; extra == "dev"
Provides-Extra: test
Requires-Dist: pytest>=7.0.0; extra == "test"
Requires-Dist: pytest-asyncio>=0.21.0; extra == "test"
Requires-Dist: pytest-cov>=4.0.0; extra == "test"
Provides-Extra: docs
Requires-Dist: sphinx>=6.0.0; extra == "docs"
Requires-Dist: sphinx-rtd-theme>=1.0.0; extra == "docs"
Requires-Dist: myst-parser>=1.0.0; extra == "docs"
